AUTHORS.rst
CONTRIBUTING.rst
HISTORY.rst
LICENSE
MANIFEST.in
README.rst
setup.cfg
setup.py
docs/Makefile
docs/authors.rst
docs/conf.py
docs/contributing.rst
docs/history.rst
docs/index.rst
docs/installation.rst
docs/make.bat
docs/readme.rst
docs/usage.rst
pyflutter/__init__.py
pyflutter/cli.py
pyflutter/pyflutter.py
pyflutter.egg-info/PKG-INFO
pyflutter.egg-info/SOURCES.txt
pyflutter.egg-info/dependency_links.txt
pyflutter.egg-info/entry_points.txt
pyflutter.egg-info/not-zip-safe
pyflutter.egg-info/requires.txt
pyflutter.egg-info/top_level.txt
tests/__init__.py
tests/test_pyflutter.py