Metadata-Version: 1.2
Name: pyflutter
Version: 0.1.0
Summary: Write flutter in Python with FastAPI backend
Home-page: https://github.com/SpikingNeuron/pyflutter
Author: Praveen Kulkarni
Author-email: praveenneuron@gmail.com
License: BSD license
Keywords: pyflutter
Platform: UNKNOWN
Classifier: Development Status :: 2 - Pre-Alpha
Classifier: Intended Audience :: Developers
Classifier: License :: OSI Approved :: BSD License
Classifier: Natural Language :: English
Classifier: Programming Language :: Python :: 3
Classifier: Programming Language :: Python :: 3.5
Classifier: Programming Language :: Python :: 3.6
Classifier: Programming Language :: Python :: 3.7
Classifier: Programming Language :: Python :: 3.8
Requires-Python: >=3.5
